pexels_cli/__init__.py
pexels_cli/pexels_cli.py
pexels_cli-0.1.0.dist-info/METADATA
pexels_cli-0.1.0.dist-info/WHEEL
pexels_cli-0.1.0.dist-info/entry_points.txt
pexels_cli-0.1.0.dist-info/top_level.txt
pexels_cli-0.1.0.dist-info/RECORD
